pygeoutils/__init__.py
pygeoutils/_utils.py
pygeoutils/exceptions.py
pygeoutils/geotools.py
pygeoutils/print_versions.py
pygeoutils/py.typed
pygeoutils/pygeoutils.py
pygeoutils/smoothing.py
pygeoutils-0.19.5.dist-info/METADATA
pygeoutils-0.19.5.dist-info/WHEEL
pygeoutils-0.19.5.dist-info/licenses/AUTHORS.rst
pygeoutils-0.19.5.dist-info/licenses/LICENSE
pygeoutils-0.19.5.dist-info/RECORD
