Metadata-Version: 2.4
Name: pygeoutils
Version: 0.19.5
Summary: Utilities for manipulating geospatial, (Geo)JSON, and (Geo)TIFF data.
Project-URL: Changelog, https://docs.hyriver.io/changelogs/pygeoutils.html
Project-URL: CI, https://github.com/hyriver/pygeoutils/actions
Project-URL: Homepage, https://docs.hyriver.io/readme/pygeoutils.html
Project-URL: Issues, https://github.com/hyriver/pygeoutils/issues
Author-email: Taher Chegini <cheginit@gmail.com>
License: MIT
License-File: AUTHORS.rst
License-File: LICENSE
Classifier: Development Status :: 4 - Beta
Classifier: Intended Audience :: Science/Research
Classifier: License :: OSI Approved :: MIT License
Classifier: Operating System :: OS Independent
Classifier: Programming Language :: Python
Classifier: Programming Language :: Python :: 3 :: Only
Classifier: Programming Language :: Python :: 3.9
Classifier: Programming Language :: Python :: 3.10
Classifier: Programming Language :: Python :: 3.11
Classifier: Programming Language :: Python :: 3.12
Classifier: Programming Language :: Python :: 3.13
Classifier: Topic :: Scientific/Engineering
Classifier: Topic :: Scientific/Engineering :: GIS
Classifier: Topic :: Scientific/Engineering :: Hydrology
Classifier: Typing :: Typed
Requires-Python: >=3.9
Requires-Dist: cytoolz
Requires-Dist: geopandas>=1
Requires-Dist: netcdf4
Requires-Dist: numpy>=2
Requires-Dist: pyproj>=3.0.1
Requires-Dist: rasterio>=1.2
Requires-Dist: rioxarray>=0.15
Requires-Dist: scipy
Requires-Dist: shapely>=2
Requires-Dist: xarray>=2024.7
Provides-Extra: test
Requires-Dist: pytest-cov; extra == 'test'
Requires-Dist: pytest-sugar; extra == 'test'
